<?xml version="1.0"?>
<gameList>
	<game>
		<path>./Sci-Fi Classic.fpt</path>
		<name>Sci-Fi Classic</name>
		<playcount>1</playcount>
		<lastplayed>20210110T142949</lastplayed>
		<gametime>44</gametime>
		<lang>en</lang>
	</game>
	<game>
		<path>./JDG.fpt</path>
		<name>Joueur du Grenier</name>
		<playcount>4</playcount>
		<lastplayed>20210124T130908</lastplayed>
		<gametime>205</gametime>
		<lang>en</lang>
	</game>
	<game>
		<path>./Masters of the Universe (p2.5) (Mastered Edition).fpt</path>
		<name>Masters of the Universe</name>
		<playcount>1</playcount>
		<lastplayed>20210124T131212</lastplayed>
		<gametime>181</gametime>
		<lang>en</lang>
	</game>
	<game>
		<path>./Duck Tales 2.0.fpt</path>
		<name>Duck Tales 2.0</name>
		<playcount>2</playcount>
		<lastplayed>20210124T130742</lastplayed>
		<md5>27f883f60bdf13b885a77172a4160513</md5>
		<gametime>100</gametime>
		<lang>en</lang>
	</game>
	<game>
		<path>./Southern Belle (Gottlieb'55)v.1.2.fpt</path>
		<name>Southern Belle (1955)</name>
		<lang>en</lang>
	</game>
</gameList>
